my_calculator_kivemari/__init__.py
my_calculator_kivemari/calculator.py
my_calculator_kivemari-0.0.2.dist-info/WHEEL
my_calculator_kivemari-0.0.2.dist-info/METADATA
my_calculator_kivemari-0.0.2.dist-info/RECORD
